mcdis_rcon/__init__.py
mcdis_rcon/main.py
mcdis_rcon/modules.py
mcdis_rcon/__pycache__/__init__.cpython-312.pyc
mcdis_rcon/__pycache__/main.cpython-312.pyc
mcdis_rcon/__pycache__/modules.cpython-312.pyc
mcdis_rcon/behaviours/on_app_command_completion.py
mcdis_rcon/behaviours/on_audit_log_entry_create.py
mcdis_rcon/behaviours/on_automod_action.py
mcdis_rcon/behaviours/on_automod_rule_create.py
mcdis_rcon/behaviours/on_automod_rule_delete.py
mcdis_rcon/behaviours/on_automod_rule_update.py
mcdis_rcon/behaviours/on_bulk_message_delete.py
mcdis_rcon/behaviours/on_connect.py
mcdis_rcon/behaviours/on_disconnect.py
mcdis_rcon/behaviours/on_error.py
mcdis_rcon/behaviours/on_guild_available.py
mcdis_rcon/behaviours/on_guild_channel_create.py
mcdis_rcon/behaviours/on_guild_channel_delete.py
mcdis_rcon/behaviours/on_guild_channel_pins_update.py
mcdis_rcon/behaviours/on_guild_channel_update.py
mcdis_rcon/behaviours/on_guild_emojis_update.py
mcdis_rcon/behaviours/on_guild_integrations_update.py
mcdis_rcon/behaviours/on_guild_join.py
mcdis_rcon/behaviours/on_guild_remove.py
mcdis_rcon/behaviours/on_guild_role_create.py
mcdis_rcon/behaviours/on_guild_role_delete.py
mcdis_rcon/behaviours/on_guild_role_update.py
mcdis_rcon/behaviours/on_guild_stickers_update.py
mcdis_rcon/behaviours/on_guild_unavailable.py
mcdis_rcon/behaviours/on_guild_update.py
mcdis_rcon/behaviours/on_integration_create.py
mcdis_rcon/behaviours/on_integration_update.py
mcdis_rcon/behaviours/on_interaction.py
mcdis_rcon/behaviours/on_invite_create.py
mcdis_rcon/behaviours/on_invite_delete.py
mcdis_rcon/behaviours/on_member_ban.py
mcdis_rcon/behaviours/on_member_join.py
mcdis_rcon/behaviours/on_member_remove.py
mcdis_rcon/behaviours/on_member_unban.py
mcdis_rcon/behaviours/on_member_update.py
mcdis_rcon/behaviours/on_message.py
mcdis_rcon/behaviours/on_message_delete.py
mcdis_rcon/behaviours/on_message_edit.py
mcdis_rcon/behaviours/on_presence_update.py
mcdis_rcon/behaviours/on_private_channel_pins_update.py
mcdis_rcon-0.4.31a0.dist-info/licenses/LICENSE
mcdis_rcon-0.4.31a0.dist-info/METADATA
mcdis_rcon-0.4.31a0.dist-info/WHEEL
mcdis_rcon-0.4.31a0.dist-info/entry_points.txt
mcdis_rcon-0.4.31a0.dist-info/top_level.txt
mcdis_rcon-0.4.31a0.dist-info/RECORD
