Metadata-Version: 2.4
Name: mcdis_rcon
Version: 0.4.31a0
Classifier: Programming Language :: Python :: 3.10
Classifier: Programming Language :: Python :: 3.12
Requires-Python: >=3.8
License-File: LICENSE
Requires-Dist: polib
Requires-Dist: psutil
Requires-Dist: discord.py
Requires-Dist: flask
Requires-Dist: requests
Requires-Dist: nbtlib
Requires-Dist: ruamel.yaml
Dynamic: classifier
Dynamic: description
Dynamic: description-content-type
Dynamic: license-file
Dynamic: requires-dist
Dynamic: requires-python
